bluepie/__init__.py
bluepie/ble_device.py
bluepie/logs.py
bluepie/nus_device.py
bluepie-1.0.0.dist-info/METADATA
bluepie-1.0.0.dist-info/WHEEL
bluepie-1.0.0.dist-info/top_level.txt
bluepie-1.0.0.dist-info/RECORD
