Metadata-Version: 2.1
Name: bluepie
Version: 1.0.0
Summary: This repository contains often used BLE wrappers around bleak.
Home-page: https://github.com/IRNAS/irnas-bluepie-software
Author: Irnas
Author-email: iot@irnas.eu
License: GPLv2
Project-URL: Bug Tracker, https://github.com/IRNAS/irnas-bluepie-software/issues
Platform: UNKNOWN
Classifier: Programming Language :: Python :: 3
Classifier: Programming Language :: Python :: 3.8
Classifier: License :: OSI Approved :: GNU General Public License v2 (GPLv2)
Classifier: Operating System :: POSIX :: Linux
Requires-Dist: bleak (>=0.14.2)
Requires-Dist: rich (>=11.2.0)
